mendeley_watchdog/__init__.py
mendeley_watchdog/main.py
mendeley_watchdog/cli/__init__.py
mendeley_watchdog/cli/mendeley.py
mendeley_watchdog/core/__init__.py
mendeley_watchdog/core/utils.py
mendeley_watchdog-0.0.2.dist-info/LICENSE
mendeley_watchdog-0.0.2.dist-info/METADATA
mendeley_watchdog-0.0.2.dist-info/WHEEL
mendeley_watchdog-0.0.2.dist-info/entry_points.txt
mendeley_watchdog-0.0.2.dist-info/top_level.txt
mendeley_watchdog-0.0.2.dist-info/RECORD
