Metadata-Version: 2.1
Name: mendeley-watchdog
Version: 0.0.2
Summary: Continuously monitor a file and mirror the content after modification
Home-page: https://github.com/vlntnwbr/mendeley-watchdog
Author: Valentin Weber
Author-email: dev@vweber.eu
License: EUPL v1.2 or later
Project-URL: Bug Tracker, https://github.com/vlntnwbr/mendeley-watchdog/issues?q=label%3bug
Project-URL: Documentation, https://github.com/vlntnwbr/mendeley-watchdog/tree/v0.0.2/docs
Platform: UNKNOWN
Classifier: Development Status :: 1 - Planning
Classifier: Environment :: Console
Classifier: Operating System :: OS Independent
Classifier: Programming Language :: Python :: 3 :: Only
Classifier: Intended Audience :: Education
Classifier: Intended Audience :: Developers
Classifier: Intended Audience :: Science/Research
Classifier: Topic :: System :: Filesystems
Classifier: Topic :: System :: Monitoring
Classifier: Topic :: Utilities
Classifier: License :: OSI Approved :: European Union Public Licence 1.2 (EUPL 1.2)
Requires-Python: >=3.8
